ACBICI/__init__.py
ACBICI/_version.py
ACBICI/calibrator.py
ACBICI/gprocess.py
ACBICI/kernels.py
ACBICI/priors.py
ACBICI/randomprocess.py
ACBICI/vbmc.py
acbici-2.1.0.dist-info/licenses/LICENSE
acbici-2.1.0.dist-info/METADATA
acbici-2.1.0.dist-info/WHEEL
acbici-2.1.0.dist-info/top_level.txt
acbici-2.1.0.dist-info/RECORD
