Metadata-Version: 2.4
Name: ACBICI
Version: 2.1.0
Summary: A Configurable BayesIan Calibration and Inference package
Author: Christina Schenk, Ignacio Romero
License: BSD-3-Clause License
Project-URL: Homepage, https://gitlab.com/schenkch/ACBICI
Classifier: Programming Language :: Python :: 3.9
Classifier: Programming Language :: Python :: 3.12
Classifier: Programming Language :: Python :: 3.13
Classifier: Programming Language :: Python :: 3.14
Requires-Python: >=3.9
License-File: LICENSE
Requires-Dist: matplotlib
Requires-Dist: scipy
Requires-Dist: pyDOE
Requires-Dist: emcee
Requires-Dist: corner
Requires-Dist: pyvbmc
Requires-Dist: tqdm
Requires-Dist: sphinx
Requires-Dist: sphinx-rtd-theme
Requires-Dist: sphinx-math-dollar
Requires-Dist: seaborn
Requires-Dist: SALib
Dynamic: license-file
